MANIFEST.in
README
README.md
requirements.txt
setup.py
vweb/__init__.py
vweb/html.py
vweb/htmlify.py
vweb/htmlpage.py
vweb/htmltable.py
vweb.egg-info/PKG-INFO
vweb.egg-info/SOURCES.txt
vweb.egg-info/dependency_links.txt
vweb.egg-info/top_level.txt