Metadata-Version: 1.1
Name: vweb
Version: 1.3-3
Summary: Simple Python Website Frame work
Home-page: https://github.com/dlink/vweb
Author: David Link
Author-email: dvlink@gmail.com
License: GNU General Public License (GPL)
Keywords: cgi,web framework
Platform: UNKNOWN
Classifier: Development Status :: 5 - Production/Stable
Classifier: Intended Audience :: Developers
Classifier: License :: OSI Approved :: GNU General Public License (GPL)
Classifier: Programming Language :: Python :: 2.7
Classifier: Topic :: Software Development :: Libraries
Classifier: Topic :: Internet :: WWW/HTTP :: WSGI :: Application
